langchain_interpreter/__init__.py
langchain_interpreter/main.py
langchain_interpreter/validation.py
langchain_interpreter-0.0.7.dist-info/METADATA
langchain_interpreter-0.0.7.dist-info/WHEEL
langchain_interpreter-0.0.7.dist-info/licenses/LICENSE
langchain_interpreter-0.0.7.dist-info/RECORD
